dscol/__init__.py
dscol/_dscol.cpython-311-x86_64-linux-gnu.so
dscol/_dscolmodule.c
dscol/_version.py
dscol/c/da.c
dscol/c/da.h
dscol/c/vec.c
dscol/c/vec.h
py_collect_kao-0.0.3.dist-info/METADATA
py_collect_kao-0.0.3.dist-info/WHEEL
py_collect_kao-0.0.3.dist-info/top_level.txt
py_collect_kao-0.0.3.dist-info/RECORD
